DeepCover_Mod/__init__.py
DeepCover_Mod/main.py
deepcover-0.1.dist-info/METADATA
deepcover-0.1.dist-info/WHEEL
deepcover-0.1.dist-info/top_level.txt
deepcover-0.1.dist-info/RECORD
